liga/__version__.py
liga/conf.py
liga/exceptions.py
liga/io.py
liga/logging.py
liga/mixin.py
liga/internal/__init__.py
liga/internal/reflection.py
liga/internal/uri_utils.py
liga/numpy/__init__.py
liga/numpy/sql.py
liga/registry/__init__.py
liga/registry/base.py
liga/registry/dummy.py
liga/registry/fs.py
liga/registry/model.py
liga/spark/__init__.py
liga/spark/types/__init__.py
liga-0.3.0.dist-info/METADATA
liga-0.3.0.dist-info/WHEEL
liga-0.3.0.dist-info/namespace_packages.txt
liga-0.3.0.dist-info/top_level.txt
liga-0.3.0.dist-info/RECORD
