Metadata-Version: 2.1
Name: liga
Version: 0.3.0
Requires-Python: <3.10,>=3.8
Requires-Dist: fsspec (==2022.1.0)
Requires-Dist: jsonschema
Requires-Dist: numpy
Requires-Dist: pandas
Requires-Dist: py4j
Requires-Dist: pyarrow (>=6.0)
Requires-Dist: pyspark (==3.2.1)
Requires-Dist: pyyaml
Requires-Dist: requests
